GuxiCoverWomeiyitian/README.md
GuxiCoverWomeiyitian/__init__.py
GuxiCoverWomeiyitian/__main__.py
GuxiCoverWomeiyitian/file.epub
GuxiCoverWomeiyitian/index.html
GuxiCoverWomeiyitian/css/__init__.py
GuxiCoverWomeiyitian/css/annotations.css
GuxiCoverWomeiyitian/css/main.css
GuxiCoverWomeiyitian/css/normalize.css
GuxiCoverWomeiyitian/css/popup.css
GuxiCoverWomeiyitian/font/__init__.py
GuxiCoverWomeiyitian/font/fontello.eot
GuxiCoverWomeiyitian/font/fontello.svg
GuxiCoverWomeiyitian/font/fontello.ttf
GuxiCoverWomeiyitian/font/fontello.woff
GuxiCoverWomeiyitian/img/__init__.py
GuxiCoverWomeiyitian/img/annotator-glyph-sprite.png
GuxiCoverWomeiyitian/img/annotator-icon-sprite.png
GuxiCoverWomeiyitian/img/apple-touch-icon.png
GuxiCoverWomeiyitian/img/cancelfullscreen.png
GuxiCoverWomeiyitian/img/close.png
GuxiCoverWomeiyitian/img/fullscreen.png
GuxiCoverWomeiyitian/img/loader.gif
GuxiCoverWomeiyitian/img/menu-icon.png
GuxiCoverWomeiyitian/img/save.png
GuxiCoverWomeiyitian/img/saved.png
GuxiCoverWomeiyitian/img/settings-s.png
GuxiCoverWomeiyitian/img/settings.png
GuxiCoverWomeiyitian/img/star.png
GuxiCoverWomeiyitian/js/__init__.py
GuxiCoverWomeiyitian/js/epub.js
GuxiCoverWomeiyitian/js/epub.min.js
GuxiCoverWomeiyitian/js/epub.min.map
GuxiCoverWomeiyitian/js/hooks.min.js
GuxiCoverWomeiyitian/js/hooks.min.map
GuxiCoverWomeiyitian/js/reader.js
GuxiCoverWomeiyitian/js/reader.js.map
GuxiCoverWomeiyitian/js/reader.min.js
GuxiCoverWomeiyitian/js/reader.min.map
GuxiCoverWomeiyitian/js/hooks/__init__.py
GuxiCoverWomeiyitian/js/hooks/extensions/__init__.py
GuxiCoverWomeiyitian/js/hooks/extensions/highlight.js
GuxiCoverWomeiyitian/js/libs/__init__.py
GuxiCoverWomeiyitian/js/libs/jquery.min.js
GuxiCoverWomeiyitian/js/libs/localforage.min.js
GuxiCoverWomeiyitian/js/libs/screenfull.js
GuxiCoverWomeiyitian/js/libs/screenfull.min.js
GuxiCoverWomeiyitian/js/libs/zip.min.js
GuxiCoverWomeiyitian/js/plugins/__init__.py
GuxiCoverWomeiyitian/js/plugins/hypothesis.js
guxi_cover_womeiyitian-2022.10.15.0.dist-info/METADATA
guxi_cover_womeiyitian-2022.10.15.0.dist-info/WHEEL
guxi_cover_womeiyitian-2022.10.15.0.dist-info/entry_points.txt
guxi_cover_womeiyitian-2022.10.15.0.dist-info/top_level.txt
guxi_cover_womeiyitian-2022.10.15.0.dist-info/RECORD
